epcrawler/__init__.py
epcrawler/__main__.py
epcrawler/epcrawler.py
epcrawler/test_anime_finder.py
epcrawler-1.2.dist-info/LICENSE
epcrawler-1.2.dist-info/METADATA
epcrawler-1.2.dist-info/WHEEL
epcrawler-1.2.dist-info/entry_points.txt
epcrawler-1.2.dist-info/top_level.txt
epcrawler-1.2.dist-info/RECORD
