Metadata-Version: 2.1
Name: epcrawler
Version: 1.2
Summary: Scraper to extract episode names from anidb
Home-page: https://github.com/dgsmiley18/epcrawler
Author: Douglas Vianna
Author-email: douglasvianna230@gmail.com
License: GPLv3
Classifier: Programming Language :: Python :: 3
Classifier: License :: OSI Approved :: GNU General Public License v3 or later (GPLv3+)
Classifier: Operating System :: OS Independent
Requires-Python: >=3.6
License-File: LICENSE
Requires-Dist: beautifulsoup4
Requires-Dist: requests
